odoo10_addon_delivery_carrier_partner-10.0.1.0.0.99.dev4-py3.8-nspkg.pth
odoo/addons/delivery_carrier_partner/README.rst
odoo/addons/delivery_carrier_partner/__init__.py
odoo/addons/delivery_carrier_partner/__manifest__.py
odoo/addons/delivery_carrier_partner/i18n/delivery_carrier_partner.pot
odoo/addons/delivery_carrier_partner/i18n/it.po
odoo/addons/delivery_carrier_partner/models/__init__.py
odoo/addons/delivery_carrier_partner/models/delivery_carrier.py
odoo/addons/delivery_carrier_partner/readme/DESCRIPTION.rst
odoo/addons/delivery_carrier_partner/static/description/icon.png
odoo/addons/delivery_carrier_partner/static/description/index.html
odoo/addons/delivery_carrier_partner/views/delivery_carrier_views.xml
odoo10_addon_delivery_carrier_partner-10.0.1.0.0.99.dev4.dist-info/METADATA
odoo10_addon_delivery_carrier_partner-10.0.1.0.0.99.dev4.dist-info/WHEEL
odoo10_addon_delivery_carrier_partner-10.0.1.0.0.99.dev4.dist-info/namespace_packages.txt
odoo10_addon_delivery_carrier_partner-10.0.1.0.0.99.dev4.dist-info/top_level.txt
odoo10_addon_delivery_carrier_partner-10.0.1.0.0.99.dev4.dist-info/RECORD
